{
  "metadata": {
    "name": "area",
    "categories": ["media"],
    "description": "The <area> HTML element defines an area inside an image map that has predefined clickable areas. An image map allows geometric areas on an image to be associated with hypertext links.",
    "link": "https://developer.mozilla.org/en-US/docs/Web/HTML/Reference/Elements/area",
    "aliases": ["imagemap-area"],
    "isVoid": true,
    "interfaces": [
      "HTMLAreaElement",
      "HTMLElement",
      "Element",
      "Node",
      "EventTarget",
      "global"
    ]
  },
  "element": {
    "type": "nodes",
    "source": "catalog",
    "nodes": {
      "root": {
        "tag": "area",
        "type": "element",
        "attrs": {
          "alt": {
            "type": "value",
            "value": ""
          },
          "coords": {
            "type": "value",
            "value": ""
          },
          "shape": {
            "type": "value",
            "value": "rect"
          }
        },
        "style": {},
        "events": {},
        "classes": {},
        "children": [],
        "style-variables": []
      }
    }
  }
}
