{
  "metadata": {
    "name": "ellipse",
    "categories": ["svg"],
    "description": "The <ellipse> SVG element is an SVG basic shape, used to create ellipses based on a center coordinate, and both their x and y radius.",
    "link": "https://developer.mozilla.org/en-US/docs/Web/SVG/Reference/Element/ellipse",
    "aliases": ["oval", "svg-ellipse"],
    "interfaces": [
      "SVGEllipseElement",
      "SVGGeometryElement",
      "SVGGraphicsElement",
      "SVGElement",
      "Element",
      "Node",
      "EventTarget"
    ]
  },
  "element": {
    "type": "nodes",
    "source": "catalog",
    "nodes": {
      "root": {
        "tag": "ellipse",
        "type": "element",
        "attrs": {},
        "style": {},
        "events": {},
        "classes": {},
        "children": []
      }
    }
  }
}
