{
  "metadata": {
    "name": "feComposite",
    "categories": ["svg"],
    "description": "The <feComposite> SVG filter primitive performs the combination of two input images pixel-wise in image space using one of the Porter-Duff compositing operations: over, in, atop, out, xor, lighter, or arithmetic.",
    "link": "https://developer.mozilla.org/en-US/docs/Web/SVG/Reference/Element/feComposite",
    "aliases": ["composite-filter", "svg-composite"],
    "interfaces": [
      "SVGFECompositeElement",
      "SVGElement",
      "Element",
      "Node",
      "EventTarget"
    ]
  },
  "element": {
    "type": "nodes",
    "source": "catalog",
    "nodes": {
      "root": {
        "tag": "feComposite",
        "type": "element",
        "attrs": {},
        "style": {},
        "events": {},
        "classes": {},
        "children": []
      }
    }
  }
}
